postgres_csv_uploader/__init__.py
postgres_csv_uploader/uploader.py
postgres_csv_uploader-0.2.0.dist-info/LICENSE
postgres_csv_uploader-0.2.0.dist-info/METADATA
postgres_csv_uploader-0.2.0.dist-info/WHEEL
postgres_csv_uploader-0.2.0.dist-info/top_level.txt
postgres_csv_uploader-0.2.0.dist-info/RECORD
