Metadata-Version: 2.1
Name: postgres-csv-uploader
Version: 0.2.0
Summary: A small utility to upload CSVs to Postgres without needing to specify the table schema
Author-email: Kanyes Thaker <kanyes.thaker@gmail.com>
License: MIT
Classifier: Programming Language :: Python :: 3
Classifier: License :: OSI Approved :: MIT License
Classifier: Operating System :: MacOS
Requires-Python: >=3.7
License-File: LICENSE
Requires-Dist: numpy (>=1.23.2)
Requires-Dist: pandas (>=1.4.4)
Requires-Dist: psycopg2 (>=2.7.7)
Requires-Dist: SQLAlchemy (>=1.4.41)
